drb/drivers/tar/__init__.py
drb/drivers/tar/_version.py
drb/drivers/tar/base_node.py
drb/drivers/tar/node.py
drb/exceptions/tar.py
drb/topics/tar/__init__.py
drb/topics/tar/cortex.yml
drb_driver_tar-1.3.1.dist-info/LICENCE.txt
drb_driver_tar-1.3.1.dist-info/METADATA
drb_driver_tar-1.3.1.dist-info/WHEEL
drb_driver_tar-1.3.1.dist-info/entry_points.txt
drb_driver_tar-1.3.1.dist-info/top_level.txt
drb_driver_tar-1.3.1.dist-info/RECORD
