Metadata-Version: 2.1
Name: drb-driver-tar
Version: 1.3.1
Summary: DRB Tar driver
Home-page: https://gitlab.com/drb-python/impl/tar
Author: GAEL Systems
Author-email: drb-python@gael.fr
License: LGPLv3
Project-URL: Documentation, https://drb-python.gitlab.io/impl/tar
Project-URL: Source, https://gitlab.com/drb-python/impl/tar
Classifier: Programming Language :: Python :: 3.8
Classifier: License :: OSI Approved :: GNU Lesser General Public License v3 (LGPLv3)
Classifier: Operating System :: OS Independent
Requires-Python: >=3.8
License-File: LICENCE.txt
Requires-Dist: drb ~=2.2.0
